{
  "handytarif": {
    "product": [
      {
        "link": [
          "http://www.communicationads.net/tc.php?t=10506C11907004D&product=3886"
        ],
        "product": [
          "LTE S"
        ],
        "url_moreinfo": [
          "https://www.premiumsim.de/pdf/5762/produktinformationsblatt"
        ],
        "company": [
          "PremiumSIM"
        ],
        "provider": [
          "Telefónica"
        ],
        "cost_pm": [
          "6,99"
        ],
        "mobileweb_volume": [
          "2 GB"
        ]
      },
      {
        "link": [
          "http://www.communicationads.net/tc.php?t=10506C12907004D&product=3621"
        ],
        "product": [
          "LTE All 2 GB"
        ],
        "url_moreinfo": [
          "https://www.sim.de/pdf/339/produktinformationsblatt"
        ],
        "company": [
          "sim.de"
        ],
        "provider": [
          "Telefónica"
        ],
        "cost_pm": [
          "6,99"
        ],
        "mobileweb_volume": [
          "2 GB"
        ]
      },
      {
        "link": [
          "http://www.communicationads.net/tc.php?t=10506C11907004D&product=3906"
        ],
        "product": [
          "LTE S (1 Mon.)"
        ],
        "url_moreinfo": [
          "https://www.premiumsim.de/pdf/6517/produktinformationsblatt"
        ],
        "company": [
          "PremiumSIM"
        ],
        "provider": [
          "Telefónica"
        ],
        "cost_pm": [
          "6,99"
        ],
        "mobileweb_volume": [
          "2 GB"
        ]
      },
      {
        "link": [
          "http://www.communicationads.net/tc.php?t=10506C12907004D&product=2067"
        ],
        "product": [
          "LTE All 2 GB (1 Mon.)"
        ],
        "url_moreinfo": [
          "https://www.sim.de/pdf/338/produktinformationsblatt"
        ],
        "company": [
          "sim.de"
        ],
        "provider": [
          "Telefónica"
        ],
        "cost_pm": [
          "6,99"
        ],
        "mobileweb_volume": [
          "2 GB"
        ]
      },
      {
        "link": [
          "http://www.communicationads.net/tc.php?t=10506C15207004D&product=1709"
        ],
        "product": [
          "M (24 Mon.)"
        ],
        "url_moreinfo": [
          "https://static2-blau.o9.de/blob/13311846/v=2/Binary/2_po_blau-m_20180612_1-0.pdf"
        ],
        "company": [
          "blau Mobilfunk"
        ],
        "provider": [
          "o2"
        ],
        "cost_pm": [
          "7,99"
        ],
        "mobileweb_volume": [
          "2 GB"
        ]
      },
      {
        "link": [
          "http://www.communicationads.net/tc.php?t=10506C12007004D&product=2088"
        ],
        "product": [
          "LTE All 3 + 1 GB"
        ],
        "url_moreinfo": [
          "https://www.winsim.de/pdf/3174/produktinformationsblatt"
        ],
        "company": [
          "winSIM"
        ],
        "provider": [
          "Telefónica"
        ],
        "cost_pm": [
          "7,99"
        ],
        "mobileweb_volume": [
          "4 GB"
        ]
      },
      {
        "link": [
          "http://www.communicationads.net/tc.php?t=10506C10807004D&product=3688"
        ],
        "product": [
          "LTE 3000"
        ],
        "url_moreinfo": [
          "https://www.simplytel.de/pdf/1447/produktinformationsblatt"
        ],
        "company": [
          "simply"
        ],
        "provider": [
          "Telefónica"
        ],
        "cost_pm": [
          "7,99"
        ],
        "mobileweb_volume": [
          "3 GB"
        ]
      },
      {
        "link": [
          "http://www.communicationads.net/tc.php?t=10506C10207004D&product=3990"
        ],
        "product": [
          "LTE 2000"
        ],
        "url_moreinfo": [
          "https://www.maxxim.de/pdf/1230/produktinformationsblatt"
        ],
        "company": [
          "maXXim"
        ],
        "provider": [
          "Telefónica"
        ],
        "cost_pm": [
          "8,99"
        ],
        "mobileweb_volume": [
          "2 GB"
        ]
      },
      {
        "link": [
          "http://www.communicationads.net/tc.php?t=10506C12507004D&product=3965"
        ],
        "product": [
          "LTE 2 GB"
        ],
        "url_moreinfo": [
          "https://www.smartmobil.de/pdf/1817/produktinformationsblatt"
        ],
        "company": [
          "smartmobil.de"
        ],
        "provider": [
          "Telefónica"
        ],
        "cost_pm": [
          "7,99"
        ],
        "mobileweb_volume": [
          "2 GB"
        ]
      },
      {
        "link": [
          "http://www.communicationads.net/tc.php?t=10506C12507004D&product=3966"
        ],
        "product": [
          "LTE 2 GB (1 Mon.)"
        ],
        "url_moreinfo": [
          "https://www.smartmobil.de/pdf/1884/produktinformationsblatt"
        ],
        "company": [
          "smartmobil.de"
        ],
        "provider": [
          "Telefónica"
        ],
        "cost_pm": [
          "7,99"
        ],
        "mobileweb_volume": [
          "2 GB"
        ]
      },
      {
        "link": [
          "http://www.communicationads.net/tc.php?t=10506C18007004D&product=1701"
        ],
        "product": [
          "freeSMART 2000 (24 Mon.)"
        ],
        "url_moreinfo": [
          "https://www.freenetmobile.de/pdf/smartphone-flat/freenetmobile_freesmart24_2_2000_42-2_1499_799_999_pib.pdf"
        ],
        "company": [
          "freenet mobile"
        ],
        "provider": [
          "D2"
        ],
        "cost_pm": [
          "7,99"
        ],
        "mobileweb_volume": [
          "2 GB"
        ]
      },
      {
        "link": [
          "http://www.communicationads.net/tc.php?t=10506C12007004D&product=2091"
        ],
        "product": [
          "LTE All 3 + 1 GB (1 Mon.)"
        ],
        "url_moreinfo": [
          "https://www.winsim.de/pdf/3173/produktinformationsblatt"
        ],
        "company": [
          "winSIM"
        ],
        "provider": [
          "Telefónica"
        ],
        "cost_pm": [
          "7,99"
        ],
        "mobileweb_volume": [
          "4 GB"
        ]
      },
      {
        "link": [
          "http://www.communicationads.net/tc.php?t=10506C11407004D&product=2014"
        ],
        "product": [
          "Flat S"
        ],
        "url_moreinfo": [
          "https://www.discotel.de/pdf/672/produktinformationsblatt"
        ],
        "company": [
          "discoTEL"
        ],
        "provider": [
          "Telefónica"
        ],
        "cost_pm": [
          "8,61"
        ],
        "mobileweb_volume": [
          "2 GB"
        ]
      },
      {
        "link": [
          "http://www.communicationads.net/tc.php?t=10506C12507004D&product=4151"
        ],
        "product": [
          "Flat S"
        ],
        "url_moreinfo": [
          "https://www.smartmobil.de/pdf/2338/produktinformationsblatt"
        ],
        "company": [
          "smartmobil.de"
        ],
        "provider": [
          "Telefónica"
        ],
        "cost_pm": [
          "8,61"
        ],
        "mobileweb_volume": [
          "2 GB"
        ]
      }
    ]
  }
}
